pywry-0.6.2.dist-info/METADATA
pywry-0.6.2.dist-info/WHEEL
pywry-0.6.2.dist-info/license_files/LICENSE
pywry/backend.py
pywry/__init__.py
pywry/core.py
pywry/py.typed
pywry/pywry.pyi
pywry-0.6.2.data/scripts/pywry
pywry-0.6.2.dist-info/RECORD
